xled/__init__.py
xled/__version__.py
xled/auth.py
xled/cli.py
xled/compat.py
xled/control.py
xled/device.py
xled/discover.py
xled/exceptions.py
xled/response.py
xled/security.py
xled/udp_client.py
xled/util.py
xled-0.7.0.dist-info/AUTHORS.rst
xled-0.7.0.dist-info/LICENSE
xled-0.7.0.dist-info/METADATA
xled-0.7.0.dist-info/WHEEL
xled-0.7.0.dist-info/entry_points.txt
xled-0.7.0.dist-info/top_level.txt
xled-0.7.0.dist-info/RECORD
