Metadata-Version: 2.1
Name: xled
Version: 0.7.0
Summary: Python library and command line interface to control Twinkly - Smart Decoration LED lights for Christmas.
Home-page: https://github.com/scrool/xled
Author: Pavol Babinčák
Author-email: scroolik@gmail.com
License: MIT license
Project-URL: Documentation, https://xled.readthedocs.io/
Project-URL: Source, https://github.com/scrool/xled
Project-URL: Chanelog, https://xled.readthedocs.io/en/latest/history.html
Keywords: xled,twinkly
Platform: UNKNOWN
Classifier: Development Status :: 2 - Pre-Alpha
Classifier: Intended Audience :: Developers
Classifier: License :: OSI Approved :: MIT License
Classifier: Natural Language :: English
Classifier: Operating System :: POSIX :: Linux
Classifier: Programming Language :: Python :: 2
Classifier: Programming Language :: Python :: 2.7
Classifier: Programming Language :: Python :: 3
Classifier: Programming Language :: Python :: 3.6
Classifier: Programming Language :: Python :: 3.7
Classifier: Programming Language :: Python :: 3.8
Classifier: Programming Language :: Python :: 3.9
Classifier: Programming Language :: Python :: 3.10
Requires-Python: >=2.7,!=3.0.*,!=3.1.*,!=3.2,!=3.3,!=3.4,!=3.5
Provides-Extra: tests
License-File: LICENSE
License-File: AUTHORS.rst
